{
  "experiment_id": "BATT4c_lfp_narrow_dynamic_pilot",
  "status": "complete",
  "config": {
    "experiment_id": "BATT4c_lfp_narrow_dynamic_pilot",
    "description": "Narrow no-intercept q_tau dynamic residual pilot on top of the physics-filtered BATT-4a R0(T) slot.",
    "source_dataset": "battery_lfp_ocv_dyn",
    "source_url": "https://data.mendeley.com/datasets/p8kf893yv3/1",
    "source_doi": "10.17632/p8kf893yv3.1",
    "license": "CC BY 4.0",
    "baseline_experiment": "BATT4a2_lfp_filtered_r0_slot_ecm",
    "diagnostic_experiment": "BATT4b_lfp_r0_residual_diagnostics",
    "base_model": "BATT4a2_R0T_physical",
    "selected_r0_model": "BATT4a_R0_slot_filtered_T_only_STLSQ_dense",
    "selected_feature_set": "T_only",
    "ocv_curve": "discharge",
    "current_convention": "I_model=I_raw",
    "dynamic_model_form": "Vhat = OCV_discharge(s,T) - R0(T) I - k q_tau; q_tau[k+1]=exp(-dt/tau) q_tau[k] + (1-exp(-dt/tau)) I[k]",
    "dynamic_tau_grid_s": [
      20.0,
      50.0,
      100.0,
      200.0,
      500.0,
      1000.0
    ],
    "gain_fit": "no_intercept_train_residual_lstsq",
    "selection_rule": "Select the lowest validation-temperature RMSE among q_tau candidates that do not worsen validation RMSE relative to R0(T).",
    "fit_stride": 20,
    "prediction_sample_stride": 30,
    "score_start_s": 300.0,
    "initialization_window_s": 300.0
  },
  "r0_coefficients_ohm": [
    0.05050618031070004,
    -0.09215239927755273,
    0.043552000980923294
  ],
  "base_model_split_rows": [
    {
      "model": "BATT4a2_R0T_physical",
      "split": "test_cell_transfer",
      "tau_s": "",
      "dynamic_gain_ohm": 0.0,
      "n_score": 47086,
      "dynamic_correction_rms_mv": 0.0,
      "r0_min_ohm": 0.0019057820140706075,
      "r0_max_ohm": 0.0019057820140706075,
      "r0_negative_fraction": 0.0,
      "rmse_mv": 436.5653478288773,
      "mae_mv": 243.46159645083506,
      "max_abs_mv": 1315.4671542133422,
      "bias_mv": 233.95348820370864,
      "nrmse": 1.0955378846143384
    },
    {
      "model": "BATT4a2_R0T_physical",
      "split": "test_high_amplitude",
      "tau_s": "",
      "dynamic_gain_ohm": 0.0,
      "n_score": 39460,
      "dynamic_correction_rms_mv": 0.0,
      "r0_min_ohm": 0.0019057820140706075,
      "r0_max_ohm": 0.0019057820140706075,
      "r0_negative_fraction": 0.0,
      "rmse_mv": 24.06134807798182,
      "mae_mv": 14.339160262208575,
      "max_abs_mv": 261.43831964685836,
      "bias_mv": 0.8656026704887543,
      "nrmse": 0.5338626404379215
    },
    {
      "model": "BATT4a2_R0T_physical",
      "split": "train",
      "tau_s": "",
      "dynamic_gain_ohm": 0.0,
      "n_score": 263165,
      "dynamic_correction_rms_mv": 0.0,
      "r0_min_ohm": 0.0019057820140706075,
      "r0_max_ohm": 0.18621058056917605,
      "r0_negative_fraction": 0.0,
      "rmse_mv": 41.64424472520614,
      "mae_mv": 22.005517854163095,
      "max_abs_mv": 410.9955136382819,
      "bias_mv": 0.2501433346810842,
      "nrmse": 0.20541000980868473
    },
    {
      "model": "BATT4a2_R0T_physical",
      "split": "validation_temperature",
      "tau_s": "",
      "dynamic_gain_ohm": 0.0,
      "n_score": 186800,
      "dynamic_correction_rms_mv": 0.0,
      "r0_min_ohm": 0.006854743244735878,
      "r0_max_ohm": 0.12147634023036406,
      "r0_negative_fraction": 0.0,
      "rmse_mv": 71.83994372929314,
      "mae_mv": 46.220054211666046,
      "max_abs_mv": 395.9737558138752,
      "bias_mv": -1.6142531221209424,
      "nrmse": 0.4267132225867447
    }
  ],
  "candidate_scan": [
    {
      "model": "BATT4c_R0T_qtau20s_no_intercept",
      "tau_s": 20.0,
      "dynamic_gain_ohm": 0.014949254974321502,
      "test_cell_transfer_rmse_mv": 436.2850580136113,
      "test_cell_transfer_improvement_percent": 0.06420340429214282,
      "test_high_amplitude_rmse_mv": 19.64346915763581,
      "test_high_amplitude_improvement_percent": 18.36089526666523,
      "train_rmse_mv": 41.14265894793823,
      "train_improvement_percent": 1.2044540141805387,
      "validation_temperature_rmse_mv": 71.38897995134568,
      "validation_temperature_improvement_percent": 0.6277340356039024
    },
    {
      "model": "BATT4c_R0T_qtau50s_no_intercept",
      "tau_s": 50.0,
      "dynamic_gain_ohm": 0.016221295236863928,
      "test_cell_transfer_rmse_mv": 436.28839473978826,
      "test_cell_transfer_improvement_percent": 0.06343909118448686,
      "test_high_amplitude_rmse_mv": 21.539622091974323,
      "test_high_amplitude_improvement_percent": 10.480401920269339,
      "train_rmse_mv": 41.135583291653184,
      "train_improvement_percent": 1.2214447324220046,
      "validation_temperature_rmse_mv": 71.38454849269397,
      "validation_temperature_improvement_percent": 0.6339025519217987
    },
    {
      "model": "BATT4c_R0T_qtau100s_no_intercept",
      "tau_s": 100.0,
      "dynamic_gain_ohm": 0.01689429189431583,
      "test_cell_transfer_rmse_mv": 436.2821879778235,
      "test_cell_transfer_improvement_percent": 0.06486081693427463,
      "test_high_amplitude_rmse_mv": 22.4500995069826,
      "test_high_amplitude_improvement_percent": 6.696418528908814,
      "train_rmse_mv": 41.14406704352685,
      "train_improvement_percent": 1.2010727652278579,
      "validation_temperature_rmse_mv": 71.40559509517027,
      "validation_temperature_improvement_percent": 0.6046060333226035
    },
    {
      "model": "BATT4c_R0T_qtau200s_no_intercept",
      "tau_s": 200.0,
      "dynamic_gain_ohm": 0.017363923387553284,
      "test_cell_transfer_rmse_mv": 436.2695624171052,
      "test_cell_transfer_improvement_percent": 0.06775283774653634,
      "test_high_amplitude_rmse_mv": 23.04467689596445,
      "test_high_amplitude_improvement_percent": 4.22532926551904,
      "train_rmse_mv": 41.190597287269235,
      "train_improvement_percent": 1.0893400539026408,
      "validation_temperature_rmse_mv": 71.44604694679968,
      "validation_temperature_improvement_percent": 0.5482977324950811
    },
    {
      "model": "BATT4c_R0T_qtau500s_no_intercept",
      "tau_s": 500.0,
      "dynamic_gain_ohm": 0.01452869166853324,
      "test_cell_transfer_rmse_mv": 436.2986720912233,
      "test_cell_transfer_improvement_percent": 0.06108495302713029,
      "test_high_amplitude_rmse_mv": 23.64741566090094,
      "test_high_amplitude_improvement_percent": 1.7203209717898662,
      "train_rmse_mv": 41.420356853965245,
      "train_improvement_percent": 0.5376201987051149,
      "validation_temperature_rmse_mv": 71.68306421713693,
      "validation_temperature_improvement_percent": 0.2183736567881532
    },
    {
      "model": "BATT4c_R0T_qtau1000s_no_intercept",
      "tau_s": 1000.0,
      "dynamic_gain_ohm": 0.009743947470198844,
      "test_cell_transfer_rmse_mv": 436.3581579114365,
      "test_cell_transfer_improvement_percent": 0.04745908452679753,
      "test_high_amplitude_rmse_mv": 23.89991226897594,
      "test_high_amplitude_improvement_percent": 0.6709341824185137,
      "train_rmse_mv": 41.569974653675786,
      "train_improvement_percent": 0.178344143399492,
      "validation_temperature_rmse_mv": 71.83008664994217,
      "validation_temperature_improvement_percent": 0.013720889576568331
    }
  ],
  "selected_by_validation": {
    "model": "BATT4c_R0T_qtau50s_no_intercept",
    "tau_s": 50.0,
    "dynamic_gain_ohm": 0.016221295236863928,
    "test_cell_transfer_rmse_mv": 436.28839473978826,
    "test_cell_transfer_improvement_percent": 0.06343909118448686,
    "test_high_amplitude_rmse_mv": 21.539622091974323,
    "test_high_amplitude_improvement_percent": 10.480401920269339,
    "train_rmse_mv": 41.135583291653184,
    "train_improvement_percent": 1.2214447324220046,
    "validation_temperature_rmse_mv": 71.38454849269397,
    "validation_temperature_improvement_percent": 0.6339025519217987
  },
  "selected_by_high_amplitude": {
    "model": "BATT4c_R0T_qtau20s_no_intercept",
    "tau_s": 20.0,
    "dynamic_gain_ohm": 0.014949254974321502,
    "test_cell_transfer_rmse_mv": 436.2850580136113,
    "test_cell_transfer_improvement_percent": 0.06420340429214282,
    "test_high_amplitude_rmse_mv": 19.64346915763581,
    "test_high_amplitude_improvement_percent": 18.36089526666523,
    "train_rmse_mv": 41.14265894793823,
    "train_improvement_percent": 1.2044540141805387,
    "validation_temperature_rmse_mv": 71.38897995134568,
    "validation_temperature_improvement_percent": 0.6277340356039024
  },
  "split_summary": {
    "BATT4a2_R0T_physical:test_cell_transfer": {
      "model": "BATT4a2_R0T_physical",
      "split": "test_cell_transfer",
      "tau_s": "",
      "dynamic_gain_ohm": 0.0,
      "n_score": 47086,
      "dynamic_correction_rms_mv": 0.0,
      "r0_min_ohm": 0.0019057820140706075,
      "r0_max_ohm": 0.0019057820140706075,
      "r0_negative_fraction": 0.0,
      "rmse_mv": 436.5653478288773,
      "mae_mv": 243.46159645083506,
      "max_abs_mv": 1315.4671542133422,
      "bias_mv": 233.95348820370864,
      "nrmse": 1.0955378846143384
    },
    "BATT4a2_R0T_physical:test_high_amplitude": {
      "model": "BATT4a2_R0T_physical",
      "split": "test_high_amplitude",
      "tau_s": "",
      "dynamic_gain_ohm": 0.0,
      "n_score": 39460,
      "dynamic_correction_rms_mv": 0.0,
      "r0_min_ohm": 0.0019057820140706075,
      "r0_max_ohm": 0.0019057820140706075,
      "r0_negative_fraction": 0.0,
      "rmse_mv": 24.06134807798182,
      "mae_mv": 14.339160262208575,
      "max_abs_mv": 261.43831964685836,
      "bias_mv": 0.8656026704887543,
      "nrmse": 0.5338626404379215
    },
    "BATT4a2_R0T_physical:train": {
      "model": "BATT4a2_R0T_physical",
      "split": "train",
      "tau_s": "",
      "dynamic_gain_ohm": 0.0,
      "n_score": 263165,
      "dynamic_correction_rms_mv": 0.0,
      "r0_min_ohm": 0.0019057820140706075,
      "r0_max_ohm": 0.18621058056917605,
      "r0_negative_fraction": 0.0,
      "rmse_mv": 41.64424472520614,
      "mae_mv": 22.005517854163095,
      "max_abs_mv": 410.9955136382819,
      "bias_mv": 0.2501433346810842,
      "nrmse": 0.20541000980868473
    },
    "BATT4a2_R0T_physical:validation_temperature": {
      "model": "BATT4a2_R0T_physical",
      "split": "validation_temperature",
      "tau_s": "",
      "dynamic_gain_ohm": 0.0,
      "n_score": 186800,
      "dynamic_correction_rms_mv": 0.0,
      "r0_min_ohm": 0.006854743244735878,
      "r0_max_ohm": 0.12147634023036406,
      "r0_negative_fraction": 0.0,
      "rmse_mv": 71.83994372929314,
      "mae_mv": 46.220054211666046,
      "max_abs_mv": 395.9737558138752,
      "bias_mv": -1.6142531221209424,
      "nrmse": 0.4267132225867447
    },
    "BATT4c_R0T_qtau20s_no_intercept:test_cell_transfer": {
      "model": "BATT4c_R0T_qtau20s_no_intercept",
      "split": "test_cell_transfer",
      "tau_s": 20.0,
      "dynamic_gain_ohm": 0.014949254974321502,
      "n_score": 47086,
      "dynamic_correction_rms_mv": 5.591319043197691,
      "r0_min_ohm": 0.0019057820140706075,
      "r0_max_ohm": 0.0019057820140706075,
      "r0_negative_fraction": 0.0,
      "rmse_mv": 436.2850580136113,
      "mae_mv": 242.99041661352447,
      "max_abs_mv": 1315.4219994705272,
      "bias_mv": 231.7632521636066,
      "nrmse": 1.094834511997106
    },
    "BATT4c_R0T_qtau20s_no_intercept:test_high_amplitude": {
      "model": "BATT4c_R0T_qtau20s_no_intercept",
      "split": "test_high_amplitude",
      "tau_s": 20.0,
      "dynamic_gain_ohm": 0.014949254974321502,
      "n_score": 39460,
      "dynamic_correction_rms_mv": 10.673476503260131,
      "r0_min_ohm": 0.0019057820140706075,
      "r0_max_ohm": 0.0019057820140706075,
      "r0_negative_fraction": 0.0,
      "rmse_mv": 19.64346915763581,
      "mae_mv": 10.712589246091289,
      "max_abs_mv": 261.43831964685836,
      "bias_mv": -1.9448505991757228,
      "nrmse": 0.43584068015926125
    },
    "BATT4c_R0T_qtau20s_no_intercept:train": {
      "model": "BATT4c_R0T_qtau20s_no_intercept",
      "split": "train",
      "tau_s": 20.0,
      "dynamic_gain_ohm": 0.014949254974321502,
      "n_score": 263165,
      "dynamic_correction_rms_mv": 6.443968763619014,
      "r0_min_ohm": 0.0019057820140706075,
      "r0_max_ohm": 0.18621058056917605,
      "r0_negative_fraction": 0.0,
      "rmse_mv": 41.14265894793823,
      "mae_mv": 21.566993684334907,
      "max_abs_mv": 410.9955136382819,
      "bias_mv": -2.873796395628005,
      "nrmse": 0.20293594070001542
    },
    "BATT4c_R0T_qtau20s_no_intercept:validation_temperature": {
      "model": "BATT4c_R0T_qtau20s_no_intercept",
      "split": "validation_temperature",
      "tau_s": 20.0,
      "dynamic_gain_ohm": 0.014949254974321502,
      "n_score": 186800,
      "dynamic_correction_rms_mv": 6.536676477462756,
      "r0_min_ohm": 0.006854743244735878,
      "r0_max_ohm": 0.12147634023036406,
      "r0_negative_fraction": 0.0,
      "rmse_mv": 71.38897995134568,
      "mae_mv": 46.42366816553212,
      "max_abs_mv": 387.3988886684856,
      "bias_mv": -4.763408360524973,
      "nrmse": 0.42403459845414543
    },
    "BATT4c_R0T_qtau50s_no_intercept:test_cell_transfer": {
      "model": "BATT4c_R0T_qtau50s_no_intercept",
      "split": "test_cell_transfer",
      "tau_s": 50.0,
      "dynamic_gain_ohm": 0.016221295236863928,
      "n_score": 47086,
      "dynamic_correction_rms_mv": 4.492637145614436,
      "r0_min_ohm": 0.0019057820140706075,
      "r0_max_ohm": 0.0019057820140706075,
      "r0_negative_fraction": 0.0,
      "rmse_mv": 436.28839473978826,
      "mae_mv": 243.20942558533312,
      "max_abs_mv": 1315.6169144063335,
      "bias_mv": 231.57688425849238,
      "nrmse": 1.0948428853367573
    },
    "BATT4c_R0T_qtau50s_no_intercept:test_high_amplitude": {
      "model": "BATT4c_R0T_qtau50s_no_intercept",
      "split": "test_high_amplitude",
      "tau_s": 50.0,
      "dynamic_gain_ohm": 0.016221295236863928,
      "n_score": 39460,
      "dynamic_correction_rms_mv": 7.155330848215367,
      "r0_min_ohm": 0.0019057820140706075,
      "r0_max_ohm": 0.0019057820140706075,
      "r0_negative_fraction": 0.0,
      "rmse_mv": 21.539622091974323,
      "mae_mv": 11.994556888573317,
      "max_abs_mv": 261.43831964685836,
      "bias_mv": -2.183994107881123,
      "nrmse": 0.47791169001786504
    },
    "BATT4c_R0T_qtau50s_no_intercept:train": {
      "model": "BATT4c_R0T_qtau50s_no_intercept",
      "split": "train",
      "tau_s": 50.0,
      "dynamic_gain_ohm": 0.016221295236863928,
      "n_score": 263165,
      "dynamic_correction_rms_mv": 6.488983432581963,
      "r0_min_ohm": 0.0019057820140706075,
      "r0_max_ohm": 0.18621058056917605,
      "r0_negative_fraction": 0.0,
      "rmse_mv": 41.135583291653184,
      "mae_mv": 21.695946776976843,
      "max_abs_mv": 410.9955136382819,
      "bias_mv": -3.1396129043890375,
      "nrmse": 0.20290104006400905
    },
    "BATT4c_R0T_qtau50s_no_intercept:validation_temperature": {
      "model": "BATT4c_R0T_qtau50s_no_intercept",
      "split": "validation_temperature",
      "tau_s": 50.0,
      "dynamic_gain_ohm": 0.016221295236863928,
      "n_score": 186800,
      "dynamic_correction_rms_mv": 6.536143247875651,
      "r0_min_ohm": 0.006854743244735878,
      "r0_max_ohm": 0.12147634023036406,
      "r0_negative_fraction": 0.0,
      "rmse_mv": 71.38454849269397,
      "mae_mv": 46.61064631180111,
      "max_abs_mv": 389.9662758844316,
      "bias_mv": -5.031372086531391,
      "nrmse": 0.4240082765793795
    },
    "BATT4c_R0T_qtau100s_no_intercept:test_cell_transfer": {
      "model": "BATT4c_R0T_qtau100s_no_intercept",
      "split": "test_cell_transfer",
      "tau_s": 100.0,
      "dynamic_gain_ohm": 0.01689429189431583,
      "n_score": 47086,
      "dynamic_correction_rms_mv": 4.067592405836459,
      "r0_min_ohm": 0.0019057820140706075,
      "r0_max_ohm": 0.0019057820140706075,
      "r0_negative_fraction": 0.0,
      "rmse_mv": 436.2821879778235,
      "mae_mv": 243.30857853135404,
      "max_abs_mv": 1315.5728404227707,
      "bias_mv": 231.4782903071028,
      "nrmse": 1.094827309792553
    },
    "BATT4c_R0T_qtau100s_no_intercept:test_high_amplitude": {
      "model": "BATT4c_R0T_qtau100s_no_intercept",
      "split": "test_high_amplitude",
      "tau_s": 100.0,
      "dynamic_gain_ohm": 0.01689429189431583,
      "n_score": 39460,
      "dynamic_correction_rms_mv": 5.5965449143341655,
      "r0_min_ohm": 0.0019057820140706075,
      "r0_max_ohm": 0.0019057820140706075,
      "r0_negative_fraction": 0.0,
      "rmse_mv": 22.4500995069826,
      "mae_mv": 12.85303157286971,
      "max_abs_mv": 261.43831964685836,
      "bias_mv": -2.310530430942717,
      "nrmse": 0.49811296366471475
    },
    "BATT4c_R0T_qtau100s_no_intercept:train": {
      "model": "BATT4c_R0T_qtau100s_no_intercept",
      "split": "train",
      "tau_s": 100.0,
      "dynamic_gain_ohm": 0.01689429189431583,
      "n_score": 263165,
      "dynamic_correction_rms_mv": 6.434972094005311,
      "r0_min_ohm": 0.0019057820140706075,
      "r0_max_ohm": 0.18621058056917605,
      "r0_negative_fraction": 0.0,
      "rmse_mv": 41.14406704352685,
      "mae_mv": 21.837063265623097,
      "max_abs_mv": 410.9955136382819,
      "bias_mv": -3.2802077899817066,
      "nrmse": 0.20294288612382078
    },
    "BATT4c_R0T_qtau100s_no_intercept:validation_temperature": {
      "model": "BATT4c_R0T_qtau100s_no_intercept",
      "split": "validation_temperature",
      "tau_s": 100.0,
      "dynamic_gain_ohm": 0.01689429189431583,
      "n_score": 186800,
      "dynamic_correction_rms_mv": 6.469453001295026,
      "r0_min_ohm": 0.006854743244735878,
      "r0_max_ohm": 0.12147634023036406,
      "r0_negative_fraction": 0.0,
      "rmse_mv": 71.40559509517027,
      "mae_mv": 46.76587713665327,
      "max_abs_mv": 390.7109042890471,
      "bias_mv": -5.173151825960442,
      "nrmse": 0.42413328869799993
    },
    "BATT4c_R0T_qtau200s_no_intercept:test_cell_transfer": {
      "model": "BATT4c_R0T_qtau200s_no_intercept",
      "split": "test_cell_transfer",
      "tau_s": 200.0,
      "dynamic_gain_ohm": 0.017363923387553284,
      "n_score": 47086,
      "dynamic_correction_rms_mv": 3.7688414039960176,
      "r0_min_ohm": 0.0019057820140706075,
      "r0_max_ohm": 0.0019057820140706075,
      "r0_negative_fraction": 0.0,
      "rmse_mv": 436.2695624171052,
      "mae_mv": 243.37299276896275,
      "max_abs_mv": 1315.5218362587145,
      "bias_mv": 231.40951394256157,
      "nrmse": 1.0947956266089238
    },
    "BATT4c_R0T_qtau200s_no_intercept:test_high_amplitude": {
      "model": "BATT4c_R0T_qtau200s_no_intercept",
      "split": "test_high_amplitude",
      "tau_s": 200.0,
      "dynamic_gain_ohm": 0.017363923387553284,
      "n_score": 39460,
      "dynamic_correction_rms_mv": 4.709220962515788,
      "r0_min_ohm": 0.0019057820140706075,
      "r0_max_ohm": 0.0019057820140706075,
      "r0_negative_fraction": 0.0,
      "rmse_mv": 23.04467689596445,
      "mae_mv": 13.570945980039701,
      "max_abs_mv": 261.43831964685836,
      "bias_mv": -2.398281484371022,
      "nrmse": 0.5113051860538254
    },
    "BATT4c_R0T_qtau200s_no_intercept:train": {
      "model": "BATT4c_R0T_qtau200s_no_intercept",
      "split": "train",
      "tau_s": 200.0,
      "dynamic_gain_ohm": 0.017363923387553284,
      "n_score": 263165,
      "dynamic_correction_rms_mv": 6.130074538769353,
      "r0_min_ohm": 0.0019057820140706075,
      "r0_max_ohm": 0.18621058056917605,
      "r0_negative_fraction": 0.0,
      "rmse_mv": 41.190597287269235,
      "mae_mv": 22.110750199807605,
      "max_abs_mv": 410.9955136382819,
      "bias_mv": -3.3776242748167595,
      "nrmse": 0.2031723962971134
    },
    "BATT4c_R0T_qtau200s_no_intercept:validation_temperature": {
      "model": "BATT4c_R0T_qtau200s_no_intercept",
      "split": "validation_temperature",
      "tau_s": 200.0,
      "dynamic_gain_ohm": 0.017363923387553284,
      "n_score": 186800,
      "dynamic_correction_rms_mv": 6.159035666643733,
      "r0_min_ohm": 0.006854743244735878,
      "r0_max_ohm": 0.12147634023036406,
      "r0_negative_fraction": 0.0,
      "rmse_mv": 71.44604694679968,
      "mae_mv": 46.968476377891875,
      "max_abs_mv": 390.9886837028127,
      "bias_mv": -5.271563536390757,
      "nrmse": 0.42437356366304485
    },
    "BATT4c_R0T_qtau500s_no_intercept:test_cell_transfer": {
      "model": "BATT4c_R0T_qtau500s_no_intercept",
      "split": "test_cell_transfer",
      "tau_s": 500.0,
      "dynamic_gain_ohm": 0.01452869166853324,
      "n_score": 47086,
      "dynamic_correction_rms_mv": 2.7265067009307113,
      "r0_min_ohm": 0.0019057820140706075,
      "r0_max_ohm": 0.0019057820140706075,
      "r0_negative_fraction": 0.0,
      "rmse_mv": 436.2986720912233,
      "mae_mv": 243.39273444261823,
      "max_abs_mv": 1315.4773506449565,
      "bias_mv": 231.82499147222654,
      "nrmse": 1.0948686758121273
    },
    "BATT4c_R0T_qtau500s_no_intercept:test_high_amplitude": {
      "model": "BATT4c_R0T_qtau500s_no_intercept",
      "split": "test_high_amplitude",
      "tau_s": 500.0,
      "dynamic_gain_ohm": 0.01452869166853324,
      "n_score": 39460,
      "dynamic_correction_rms_mv": 3.206620418116132,
      "r0_min_ohm": 0.0019057820140706075,
      "r0_max_ohm": 0.0019057820140706075,
      "r0_negative_fraction": 0.0,
      "rmse_mv": 23.64741566090094,
      "mae_mv": 14.381631970976901,
      "max_abs_mv": 261.43831964685836,
      "bias_mv": -1.854184134102782,
      "nrmse": 0.5246784894739169
    },
    "BATT4c_R0T_qtau500s_no_intercept:train": {
      "model": "BATT4c_R0T_qtau500s_no_intercept",
      "split": "train",
      "tau_s": 500.0,
      "dynamic_gain_ohm": 0.01452869166853324,
      "n_score": 263165,
      "dynamic_correction_rms_mv": 4.312442095035521,
      "r0_min_ohm": 0.0019057820140706075,
      "r0_max_ohm": 0.18621058056917605,
      "r0_negative_fraction": 0.0,
      "rmse_mv": 41.420356853965245,
      "mae_mv": 22.434267107519947,
      "max_abs_mv": 410.9955136382819,
      "bias_mv": -2.775259166550905,
      "nrmse": 0.20430568410579109
    },
    "BATT4c_R0T_qtau500s_no_intercept:validation_temperature": {
      "model": "BATT4c_R0T_qtau500s_no_intercept",
      "split": "validation_temperature",
      "tau_s": 500.0,
      "dynamic_gain_ohm": 0.01452869166853324,
      "n_score": 186800,
      "dynamic_correction_rms_mv": 4.330925691639056,
      "r0_min_ohm": 0.006854743244735878,
      "r0_max_ohm": 0.12147634023036406,
      "r0_negative_fraction": 0.0,
      "rmse_mv": 71.68306421713693,
      "mae_mv": 47.113669989377435,
      "max_abs_mv": 392.20638845031266,
      "bias_mv": -4.663739186414118,
      "nrmse": 0.4257813933185834
    },
    "BATT4c_R0T_qtau1000s_no_intercept:test_cell_transfer": {
      "model": "BATT4c_R0T_qtau1000s_no_intercept",
      "split": "test_cell_transfer",
      "tau_s": 1000.0,
      "dynamic_gain_ohm": 0.009743947470198844,
      "n_score": 47086,
      "dynamic_correction_rms_mv": 1.6724288389903454,
      "r0_min_ohm": 0.0019057820140706075,
      "r0_max_ohm": 0.0019057820140706075,
      "r0_negative_fraction": 0.0,
      "rmse_mv": 436.3581579114365,
      "mae_mv": 243.4131162980787,
      "max_abs_mv": 1315.4634363740397,
      "bias_mv": 232.52610107396788,
      "nrmse": 1.0950179523636563
    },
    "BATT4c_R0T_qtau1000s_no_intercept:test_high_amplitude": {
      "model": "BATT4c_R0T_qtau1000s_no_intercept",
      "split": "test_high_amplitude",
      "tau_s": 1000.0,
      "dynamic_gain_ohm": 0.009743947470198844,
      "n_score": 39460,
      "dynamic_correction_rms_mv": 1.9236893421812347,
      "r0_min_ohm": 0.0019057820140706075,
      "r0_max_ohm": 0.0019057820140706075,
      "r0_negative_fraction": 0.0,
      "rmse_mv": 23.89991226897594,
      "mae_mv": 14.549202822438021,
      "max_abs_mv": 261.43831964685836,
      "bias_mv": -0.9377612340922863,
      "nrmse": 0.5302807734960615
    },
    "BATT4c_R0T_qtau1000s_no_intercept:train": {
      "model": "BATT4c_R0T_qtau1000s_no_intercept",
      "split": "train",
      "tau_s": 1000.0,
      "dynamic_gain_ohm": 0.009743947470198844,
      "n_score": 263165,
      "dynamic_correction_rms_mv": 2.486026151433858,
      "r0_min_ohm": 0.0019057820140706075,
      "r0_max_ohm": 0.18621058056917605,
      "r0_negative_fraction": 0.0,
      "rmse_mv": 41.569974653675786,
      "mae_mv": 22.405599946903788,
      "max_abs_mv": 410.9955136382819,
      "bias_mv": -1.7602043731686183,
      "nrmse": 0.2050436730862346
    },
    "BATT4c_R0T_qtau1000s_no_intercept:validation_temperature": {
      "model": "BATT4c_R0T_qtau1000s_no_intercept",
      "split": "validation_temperature",
      "tau_s": 1000.0,
      "dynamic_gain_ohm": 0.009743947470198844,
      "n_score": 186800,
      "dynamic_correction_rms_mv": 2.495751709360003,
      "r0_min_ohm": 0.006854743244735878,
      "r0_max_ohm": 0.12147634023036406,
      "r0_negative_fraction": 0.0,
      "rmse_mv": 71.83008664994217,
      "mae_mv": 46.915182359070414,
      "max_abs_mv": 393.7653560819765,
      "bias_mv": -3.638877655066328,
      "nrmse": 0.42665467373666494
    }
  },
  "outputs": {
    "metrics_by_trajectory_csv": "results/battery_lfp_narrow_dynamic_pilot/metrics_by_trajectory.csv",
    "metrics_by_split_csv": "results/battery_lfp_narrow_dynamic_pilot/metrics_by_split.csv",
    "candidate_scan_csv": "results/battery_lfp_narrow_dynamic_pilot/candidate_scan.csv",
    "predictions_sample_csv": "results/battery_lfp_narrow_dynamic_pilot/predictions_sample.csv",
    "fit_summary_csv": "results/battery_lfp_narrow_dynamic_pilot/fit_summary.csv",
    "metrics_json": "results/battery_lfp_narrow_dynamic_pilot/metrics.json",
    "figures": [
      "results/battery_lfp_narrow_dynamic_pilot/figures/candidate_scan.svg",
      "results/battery_lfp_narrow_dynamic_pilot/figures/candidate_scan_zh.svg",
      "results/battery_lfp_narrow_dynamic_pilot/figures/rmse_by_split.svg",
      "results/battery_lfp_narrow_dynamic_pilot/figures/rmse_by_split_zh.svg"
    ]
  }
}